voidbox/VoidBoxCloud.py
voidbox/__init__.py
voidbox-1.0.0.dist-info/licenses/LICENSE
voidbox-1.0.0.dist-info/WHEEL
voidbox-1.0.0.dist-info/METADATA
voidbox-1.0.0.dist-info/RECORD
