Metadata-Version: 2.4
Name: voidbox
Version: 1.0.0
Summary: Free cloud file storage, built on `Voidbox.alhasubji.store` API's
Author-email: AYMEN||d9c <aymenmw@proton.me>
License-Expression: MIT
License-File: LICENSE
